[
    {
        "file": "gen0d.drawio",
        "name": "main",
        "children": [
            {
                "name": "Prepare Macros",
                "id": 9
            },
            {
                "name": "Exhale Procs",
                "id": 14
            },
            {
                "name": "Split Names and Code",
                "id": 18
            },
            {
                "name": "Cleanup",
                "id": 20
            },
            {
                "name": "Read Text File",
                "id": 30
            },
            {
                "name": "Remove Drawio Noise",
                "id": 32
            },
            {
                "name": "Delete Connections Section",
                "id": 36
            },
            {
                "name": "Combine Generated Code",
                "id": 39
            },
            {
                "name": "Generate Includer",
                "id": 45
            },
            {
                "name": "Cleanup For Includer",
                "id": 49
            },
            {
                "name": "Decode",
                "id": 53
            },
            {
                "name": "Encode JSON",
                "id": 56
            }
        ],
        "connections": [
            {
                "dir": 0,
                "source": {
                    "name": "",
                    "id": 0
                },
                "source_port": "",
                "target": {
                    "name": "Read Text File",
                    "id": 30
                },
                "target_port": ""
            },
            {
                "dir": 1,
                "source": {
                    "name": "Cleanup For Includer",
                    "id": 49
                },
                "source_port": "",
                "target": {
                    "name": "Combine Generated Code",
                    "id": 39
                },
                "target_port": "inc"
            },
            {
                "dir": 1,
                "source": {
                    "name": "Remove Drawio Noise",
                    "id": 32
                },
                "source_port": "",
                "target": {
                    "name": "Encode JSON",
                    "id": 56
                },
                "target_port": ""
            },
            {
                "dir": 1,
                "source": {
                    "name": "Generate Includer",
                    "id": 45
                },
                "source_port": "",
                "target": {
                    "name": "Cleanup For Includer",
                    "id": 49
                },
                "target_port": ""
            },
            {
                "dir": 1,
                "source": {
                    "name": "Delete Connections Section",
                    "id": 36
                },
                "source_port": "",
                "target": {
                    "name": "Split Names and Code",
                    "id": 18
                },
                "target_port": ""
            },
            {
                "dir": 1,
                "source": {
                    "name": "Combine Generated Code",
                    "id": 39
                },
                "source_port": "",
                "target": {
                    "name": "Decode",
                    "id": 53
                },
                "target_port": ""
            },
            {
                "dir": 1,
                "source": {
                    "name": "Split Names and Code",
                    "id": 18
                },
                "source_port": "",
                "target": {
                    "name": "Decode",
                    "id": 53
                },
                "target_port": ""
            },
            {
                "dir": 1,
                "source": {
                    "name": "Cleanup",
                    "id": 20
                },
                "source_port": "",
                "target": {
                    "name": "Decode",
                    "id": 53
                },
                "target_port": ""
            },
            {
                "dir": 1,
                "source": {
                    "name": "Prepare Macros",
                    "id": 9
                },
                "source_port": "",
                "target": {
                    "name": "Generate Includer",
                    "id": 45
                },
                "target_port": ""
            },
            {
                "dir": 1,
                "source": {
                    "name": "Read Text File",
                    "id": 30
                },
                "source_port": "",
                "target": {
                    "name": "Remove Drawio Noise",
                    "id": 32
                },
                "target_port": ""
            },
            {
                "dir": 1,
                "source": {
                    "name": "Exhale Procs",
                    "id": 14
                },
                "source_port": "",
                "target": {
                    "name": "Cleanup",
                    "id": 20
                },
                "target_port": ""
            },
            {
                "dir": 1,
                "source": {
                    "name": "Encode JSON",
                    "id": 56
                },
                "source_port": "",
                "target": {
                    "name": "Delete Connections Section",
                    "id": 36
                },
                "target_port": ""
            },
            {
                "dir": 1,
                "source": {
                    "name": "Prepare Macros",
                    "id": 9
                },
                "source_port": "",
                "target": {
                    "name": "Exhale Procs",
                    "id": 14
                },
                "target_port": ""
            },
            {
                "dir": 2,
                "source": {
                    "name": "Encode JSON",
                    "id": 56
                },
                "source_port": "\u2717",
                "target": {
                    "name": "",
                    "id": 0
                },
                "target_port": "\u2717"
            },
            {
                "dir": 2,
                "source": {
                    "name": "Combine Generated Code",
                    "id": 39
                },
                "source_port": "\u2717",
                "target": {
                    "name": "",
                    "id": 0
                },
                "target_port": "\u2717"
            },
            {
                "dir": 2,
                "source": {
                    "name": "Remove Drawio Noise",
                    "id": 32
                },
                "source_port": "\u2717",
                "target": {
                    "name": "",
                    "id": 0
                },
                "target_port": "\u2717"
            },
            {
                "dir": 2,
                "source": {
                    "name": "Decode",
                    "id": 53
                },
                "source_port": "",
                "target": {
                    "name": "",
                    "id": 0
                },
                "target_port": ""
            },
            {
                "dir": 2,
                "source": {
                    "name": "Decode",
                    "id": 53
                },
                "source_port": "\u2717",
                "target": {
                    "name": "",
                    "id": 0
                },
                "target_port": "\u2717"
            },
            {
                "dir": 2,
                "source": {
                    "name": "Generate Includer",
                    "id": 45
                },
                "source_port": "\u2717",
                "target": {
                    "name": "",
                    "id": 0
                },
                "target_port": "\u2717"
            },
            {
                "dir": 2,
                "source": {
                    "name": "Cleanup",
                    "id": 20
                },
                "source_port": "\u2717",
                "target": {
                    "name": "",
                    "id": 0
                },
                "target_port": "\u2717"
            },
            {
                "dir": 2,
                "source": {
                    "name": "Exhale Procs",
                    "id": 14
                },
                "source_port": "\u2717",
                "target": {
                    "name": "",
                    "id": 0
                },
                "target_port": "\u2717"
            },
            {
                "dir": 2,
                "source": {
                    "name": "Delete Connections Section",
                    "id": 36
                },
                "source_port": "\u2717",
                "target": {
                    "name": "",
                    "id": 0
                },
                "target_port": "\u2717"
            },
            {
                "dir": 2,
                "source": {
                    "name": "Prepare Macros",
                    "id": 9
                },
                "source_port": "\u2717",
                "target": {
                    "name": "",
                    "id": 0
                },
                "target_port": "\u2717"
            },
            {
                "dir": 2,
                "source": {
                    "name": "Read Text File",
                    "id": 30
                },
                "source_port": "\u2717",
                "target": {
                    "name": "",
                    "id": 0
                },
                "target_port": "\u2717"
            },
            {
                "dir": 2,
                "source": {
                    "name": "Split Names and Code",
                    "id": 18
                },
                "source_port": "\u2717",
                "target": {
                    "name": "",
                    "id": 0
                },
                "target_port": "\u2717"
            },
            {
                "dir": 2,
                "source": {
                    "name": "Cleanup For Includer",
                    "id": 49
                },
                "source_port": "\u2717",
                "target": {
                    "name": "",
                    "id": 0
                },
                "target_port": "\u2717"
            }
        ]
    },
    {
        "file": "gen0d.drawio",
        "name": "Encode JSON",
        "children": [
            {
                "name": "Transpile",
                "id": 4
            },
            {
                "name": "'null.js'",
                "id": 13
            },
            {
                "name": "'encodejson.rwr'",
                "id": 16
            },
            {
                "name": "'encodejson.ohm'",
                "id": 19
            },
            {
                "name": "'encodejson'",
                "id": 22
            }
        ],
        "connections": [
            {
                "dir": 0,
                "source": {
                    "name": "",
                    "id": 0
                },
                "source_port": "",
                "target": {
                    "name": "'null.js'",
                    "id": 13
                },
                "target_port": "\u237a"
            },
            {
                "dir": 0,
                "source": {
                    "name": "",
                    "id": 0
                },
                "source_port": "",
                "target": {
                    "name": "'encodejson.rwr'",
                    "id": 16
                },
                "target_port": "\u237a"
            },
            {
                "dir": 0,
                "source": {
                    "name": "",
                    "id": 0
                },
                "source_port": "",
                "target": {
                    "name": "'encodejson.ohm'",
                    "id": 19
                },
                "target_port": "\u237a"
            },
            {
                "dir": 0,
                "source": {
                    "name": "",
                    "id": 0
                },
                "source_port": "",
                "target": {
                    "name": "'encodejson'",
                    "id": 22
                },
                "target_port": "\u237a"
            },
            {
                "dir": 0,
                "source": {
                    "name": "",
                    "id": 0
                },
                "source_port": "",
                "target": {
                    "name": "Transpile",
                    "id": 4
                },
                "target_port": "input"
            },
            {
                "dir": 1,
                "source": {
                    "name": "'null.js'",
                    "id": 13
                },
                "source_port": "\u237a",
                "target": {
                    "name": "Transpile",
                    "id": 4
                },
                "target_port": "rwrsupportfn"
            },
            {
                "dir": 1,
                "source": {
                    "name": "'encodejson.rwr'",
                    "id": 16
                },
                "source_port": "\u237a",
                "target": {
                    "name": "Transpile",
                    "id": 4
                },
                "target_port": "rwrfn"
            },
            {
                "dir": 1,
                "source": {
                    "name": "'encodejson.ohm'",
                    "id": 19
                },
                "source_port": "\u237a",
                "target": {
                    "name": "Transpile",
                    "id": 4
                },
                "target_port": "ohmfn"
            },
            {
                "dir": 1,
                "source": {
                    "name": "'encodejson'",
                    "id": 22
                },
                "source_port": "\u237a",
                "target": {
                    "name": "Transpile",
                    "id": 4
                },
                "target_port": "grammar name"
            },
            {
                "dir": 2,
                "source": {
                    "name": "Transpile",
                    "id": 4
                },
                "source_port": "",
                "target": {
                    "name": "",
                    "id": 0
                },
                "target_port": ""
            },
            {
                "dir": 2,
                "source": {
                    "name": "Transpile",
                    "id": 4
                },
                "source_port": "\u2717",
                "target": {
                    "name": "",
                    "id": 0
                },
                "target_port": "\u2717"
            }
        ]
    },
    {
        "file": "gen0d.drawio",
        "name": "Split Names and Code",
        "children": [
            {
                "name": "Transpile",
                "id": 4
            },
            {
                "name": "'namesandcodesupport.js'",
                "id": 13
            },
            {
                "name": "'namesandcode.rwr'",
                "id": 14
            },
            {
                "name": "'namesandcode.ohm'",
                "id": 17
            },
            {
                "name": "'namesandcode'",
                "id": 20
            }
        ],
        "connections": [
            {
                "dir": 0,
                "source": {
                    "name": "",
                    "id": 0
                },
                "source_port": "",
                "target": {
                    "name": "'namesandcodesupport.js'",
                    "id": 13
                },
                "target_port": "\u237a"
            },
            {
                "dir": 0,
                "source": {
                    "name": "",
                    "id": 0
                },
                "source_port": "",
                "target": {
                    "name": "'namesandcode.rwr'",
                    "id": 14
                },
                "target_port": "\u237a"
            },
            {
                "dir": 0,
                "source": {
                    "name": "",
                    "id": 0
                },
                "source_port": "",
                "target": {
                    "name": "'namesandcode'",
                    "id": 20
                },
                "target_port": "\u237a"
            },
            {
                "dir": 0,
                "source": {
                    "name": "",
                    "id": 0
                },
                "source_port": "",
                "target": {
                    "name": "Transpile",
                    "id": 4
                },
                "target_port": "input"
            },
            {
                "dir": 0,
                "source": {
                    "name": "",
                    "id": 0
                },
                "source_port": "",
                "target": {
                    "name": "'namesandcode.ohm'",
                    "id": 17
                },
                "target_port": "\u237a"
            },
            {
                "dir": 1,
                "source": {
                    "name": "'namesandcode.rwr'",
                    "id": 14
                },
                "source_port": "\u237a",
                "target": {
                    "name": "Transpile",
                    "id": 4
                },
                "target_port": "rwrfn"
            },
            {
                "dir": 1,
                "source": {
                    "name": "'namesandcode.ohm'",
                    "id": 17
                },
                "source_port": "\u237a",
                "target": {
                    "name": "Transpile",
                    "id": 4
                },
                "target_port": "ohmfn"
            },
            {
                "dir": 1,
                "source": {
                    "name": "'namesandcode'",
                    "id": 20
                },
                "source_port": "\u237a",
                "target": {
                    "name": "Transpile",
                    "id": 4
                },
                "target_port": "grammar name"
            },
            {
                "dir": 1,
                "source": {
                    "name": "'namesandcodesupport.js'",
                    "id": 13
                },
                "source_port": "\u237a",
                "target": {
                    "name": "Transpile",
                    "id": 4
                },
                "target_port": "rwrsupportfn"
            },
            {
                "dir": 2,
                "source": {
                    "name": "Transpile",
                    "id": 4
                },
                "source_port": "",
                "target": {
                    "name": "",
                    "id": 0
                },
                "target_port": ""
            },
            {
                "dir": 2,
                "source": {
                    "name": "Transpile",
                    "id": 4
                },
                "source_port": "\u2717",
                "target": {
                    "name": "",
                    "id": 0
                },
                "target_port": "\u2717"
            }
        ]
    },
    {
        "file": "gen0d.drawio",
        "name": "Delete Connections Section",
        "children": [
            {
                "name": "Transpile",
                "id": 4
            },
            {
                "name": "'null.js'",
                "id": 13
            },
            {
                "name": "'delconn.rwr'",
                "id": 16
            },
            {
                "name": "'delconn.ohm'",
                "id": 19
            },
            {
                "name": "'delconn'",
                "id": 22
            }
        ],
        "connections": [
            {
                "dir": 0,
                "source": {
                    "name": "",
                    "id": 0
                },
                "source_port": "",
                "target": {
                    "name": "'null.js'",
                    "id": 13
                },
                "target_port": "\u237a"
            },
            {
                "dir": 0,
                "source": {
                    "name": "",
                    "id": 0
                },
                "source_port": "",
                "target": {
                    "name": "'delconn.rwr'",
                    "id": 16
                },
                "target_port": "\u237a"
            },
            {
                "dir": 0,
                "source": {
                    "name": "",
                    "id": 0
                },
                "source_port": "",
                "target": {
                    "name": "'delconn.ohm'",
                    "id": 19
                },
                "target_port": "\u237a"
            },
            {
                "dir": 0,
                "source": {
                    "name": "",
                    "id": 0
                },
                "source_port": "",
                "target": {
                    "name": "'delconn'",
                    "id": 22
                },
                "target_port": "\u237a"
            },
            {
                "dir": 0,
                "source": {
                    "name": "",
                    "id": 0
                },
                "source_port": "",
                "target": {
                    "name": "Transpile",
                    "id": 4
                },
                "target_port": "input"
            },
            {
                "dir": 1,
                "source": {
                    "name": "'null.js'",
                    "id": 13
                },
                "source_port": "\u237a",
                "target": {
                    "name": "Transpile",
                    "id": 4
                },
                "target_port": "rwrsupportfn"
            },
            {
                "dir": 1,
                "source": {
                    "name": "'delconn.rwr'",
                    "id": 16
                },
                "source_port": "\u237a",
                "target": {
                    "name": "Transpile",
                    "id": 4
                },
                "target_port": "rwrfn"
            },
            {
                "dir": 1,
                "source": {
                    "name": "'delconn.ohm'",
                    "id": 19
                },
                "source_port": "\u237a",
                "target": {
                    "name": "Transpile",
                    "id": 4
                },
                "target_port": "ohmfn"
            },
            {
                "dir": 1,
                "source": {
                    "name": "'delconn'",
                    "id": 22
                },
                "source_port": "\u237a",
                "target": {
                    "name": "Transpile",
                    "id": 4
                },
                "target_port": "grammar name"
            },
            {
                "dir": 2,
                "source": {
                    "name": "Transpile",
                    "id": 4
                },
                "source_port": "",
                "target": {
                    "name": "",
                    "id": 0
                },
                "target_port": ""
            },
            {
                "dir": 2,
                "source": {
                    "name": "Transpile",
                    "id": 4
                },
                "source_port": "\u2717",
                "target": {
                    "name": "",
                    "id": 0
                },
                "target_port": "\u2717"
            }
        ]
    },
    {
        "file": "gen0d.drawio",
        "name": "Decode",
        "children": [
            {
                "name": "Transpile",
                "id": 4
            },
            {
                "name": "'null.js'",
                "id": 13
            },
            {
                "name": "'decode.rwr'",
                "id": 16
            },
            {
                "name": "'decode.ohm'",
                "id": 19
            },
            {
                "name": "'decode'",
                "id": 22
            }
        ],
        "connections": [
            {
                "dir": 0,
                "source": {
                    "name": "",
                    "id": 0
                },
                "source_port": "",
                "target": {
                    "name": "'null.js'",
                    "id": 13
                },
                "target_port": "\u237a"
            },
            {
                "dir": 0,
                "source": {
                    "name": "",
                    "id": 0
                },
                "source_port": "",
                "target": {
                    "name": "'decode.rwr'",
                    "id": 16
                },
                "target_port": "\u237a"
            },
            {
                "dir": 0,
                "source": {
                    "name": "",
                    "id": 0
                },
                "source_port": "",
                "target": {
                    "name": "'decode.ohm'",
                    "id": 19
                },
                "target_port": "\u237a"
            },
            {
                "dir": 0,
                "source": {
                    "name": "",
                    "id": 0
                },
                "source_port": "",
                "target": {
                    "name": "'decode'",
                    "id": 22
                },
                "target_port": "\u237a"
            },
            {
                "dir": 0,
                "source": {
                    "name": "",
                    "id": 0
                },
                "source_port": "",
                "target": {
                    "name": "Transpile",
                    "id": 4
                },
                "target_port": "input"
            },
            {
                "dir": 1,
                "source": {
                    "name": "'null.js'",
                    "id": 13
                },
                "source_port": "\u237a",
                "target": {
                    "name": "Transpile",
                    "id": 4
                },
                "target_port": "rwrsupportfn"
            },
            {
                "dir": 1,
                "source": {
                    "name": "'decode.rwr'",
                    "id": 16
                },
                "source_port": "\u237a",
                "target": {
                    "name": "Transpile",
                    "id": 4
                },
                "target_port": "rwrfn"
            },
            {
                "dir": 1,
                "source": {
                    "name": "'decode.ohm'",
                    "id": 19
                },
                "source_port": "\u237a",
                "target": {
                    "name": "Transpile",
                    "id": 4
                },
                "target_port": "ohmfn"
            },
            {
                "dir": 1,
                "source": {
                    "name": "'decode'",
                    "id": 22
                },
                "source_port": "\u237a",
                "target": {
                    "name": "Transpile",
                    "id": 4
                },
                "target_port": "grammar name"
            },
            {
                "dir": 2,
                "source": {
                    "name": "Transpile",
                    "id": 4
                },
                "source_port": "",
                "target": {
                    "name": "",
                    "id": 0
                },
                "target_port": ""
            },
            {
                "dir": 2,
                "source": {
                    "name": "Transpile",
                    "id": 4
                },
                "source_port": "\u2717",
                "target": {
                    "name": "",
                    "id": 0
                },
                "target_port": "\u2717"
            }
        ]
    },
    {
        "file": "gen0d.drawio",
        "name": "...",
        "children": [

        ],
        "connections": [

        ]
    },
    {
        "file": "gen0d.drawio",
        "name": "Exhale Procs",
        "children": [
            {
                "name": "Transpile",
                "id": 4
            },
            {
                "name": "'procssupport.js'",
                "id": 13
            },
            {
                "name": "'procs.rwr'",
                "id": 14
            },
            {
                "name": "'procs.ohm'",
                "id": 17
            },
            {
                "name": "'procs'",
                "id": 20
            }
        ],
        "connections": [
            {
                "dir": 0,
                "source": {
                    "name": "",
                    "id": 0
                },
                "source_port": "",
                "target": {
                    "name": "'procssupport.js'",
                    "id": 13
                },
                "target_port": "\u237a"
            },
            {
                "dir": 0,
                "source": {
                    "name": "",
                    "id": 0
                },
                "source_port": "",
                "target": {
                    "name": "'procs.rwr'",
                    "id": 14
                },
                "target_port": "\u237a"
            },
            {
                "dir": 0,
                "source": {
                    "name": "",
                    "id": 0
                },
                "source_port": "",
                "target": {
                    "name": "'procs'",
                    "id": 20
                },
                "target_port": "\u237a"
            },
            {
                "dir": 0,
                "source": {
                    "name": "",
                    "id": 0
                },
                "source_port": "",
                "target": {
                    "name": "Transpile",
                    "id": 4
                },
                "target_port": "input"
            },
            {
                "dir": 0,
                "source": {
                    "name": "",
                    "id": 0
                },
                "source_port": "",
                "target": {
                    "name": "'procs.ohm'",
                    "id": 17
                },
                "target_port": "\u237a"
            },
            {
                "dir": 1,
                "source": {
                    "name": "'procs.rwr'",
                    "id": 14
                },
                "source_port": "\u237a",
                "target": {
                    "name": "Transpile",
                    "id": 4
                },
                "target_port": "rwrfn"
            },
            {
                "dir": 1,
                "source": {
                    "name": "'procs.ohm'",
                    "id": 17
                },
                "source_port": "\u237a",
                "target": {
                    "name": "Transpile",
                    "id": 4
                },
                "target_port": "ohmfn"
            },
            {
                "dir": 1,
                "source": {
                    "name": "'procs'",
                    "id": 20
                },
                "source_port": "\u237a",
                "target": {
                    "name": "Transpile",
                    "id": 4
                },
                "target_port": "grammar name"
            },
            {
                "dir": 1,
                "source": {
                    "name": "'procssupport.js'",
                    "id": 13
                },
                "source_port": "\u237a",
                "target": {
                    "name": "Transpile",
                    "id": 4
                },
                "target_port": "rwrsupportfn"
            },
            {
                "dir": 2,
                "source": {
                    "name": "Transpile",
                    "id": 4
                },
                "source_port": "",
                "target": {
                    "name": "",
                    "id": 0
                },
                "target_port": ""
            },
            {
                "dir": 2,
                "source": {
                    "name": "Transpile",
                    "id": 4
                },
                "source_port": "\u2717",
                "target": {
                    "name": "",
                    "id": 0
                },
                "target_port": "\u2717"
            }
        ]
    },
    {
        "file": "gen0d.drawio",
        "name": "Copy of main",
        "children": [
            {
                "name": "Prepare Macros",
                "id": 9
            },
            {
                "name": "Exhale Procs",
                "id": 15
            },
            {
                "name": "Cleanup For Includer",
                "id": 19
            },
            {
                "name": "Cleanup",
                "id": 21
            },
            {
                "name": "Generate Includer",
                "id": 27
            },
            {
                "name": "Read Text File",
                "id": 33
            },
            {
                "name": "Remove Drawio Noise",
                "id": 34
            },
            {
                "name": "Combine Generated Code",
                "id": 41
            }
        ],
        "connections": [
            {
                "dir": 0,
                "source": {
                    "name": "",
                    "id": 0
                },
                "source_port": "",
                "target": {
                    "name": "Read Text File",
                    "id": 33
                },
                "target_port": ""
            },
            {
                "dir": 1,
                "source": {
                    "name": "Read Text File",
                    "id": 33
                },
                "source_port": "",
                "target": {
                    "name": "Remove Drawio Noise",
                    "id": 34
                },
                "target_port": ""
            },
            {
                "dir": 1,
                "source": {
                    "name": "Cleanup",
                    "id": 21
                },
                "source_port": "",
                "target": {
                    "name": "Combine Generated Code",
                    "id": 41
                },
                "target_port": "gen"
            },
            {
                "dir": 1,
                "source": {
                    "name": "Exhale Procs",
                    "id": 15
                },
                "source_port": "",
                "target": {
                    "name": "Cleanup",
                    "id": 21
                },
                "target_port": ""
            },
            {
                "dir": 1,
                "source": {
                    "name": "Prepare Macros",
                    "id": 9
                },
                "source_port": "",
                "target": {
                    "name": "Exhale Procs",
                    "id": 15
                },
                "target_port": ""
            },
            {
                "dir": 1,
                "source": {
                    "name": "Remove Drawio Noise",
                    "id": 34
                },
                "source_port": "",
                "target": {
                    "name": "Prepare Macros",
                    "id": 9
                },
                "target_port": ""
            },
            {
                "dir": 1,
                "source": {
                    "name": "Generate Includer",
                    "id": 27
                },
                "source_port": "",
                "target": {
                    "name": "Cleanup For Includer",
                    "id": 19
                },
                "target_port": ""
            },
            {
                "dir": 1,
                "source": {
                    "name": "Prepare Macros",
                    "id": 9
                },
                "source_port": "",
                "target": {
                    "name": "Generate Includer",
                    "id": 27
                },
                "target_port": ""
            },
            {
                "dir": 1,
                "source": {
                    "name": "Cleanup For Includer",
                    "id": 19
                },
                "source_port": "",
                "target": {
                    "name": "Combine Generated Code",
                    "id": 41
                },
                "target_port": "inc"
            },
            {
                "dir": 2,
                "source": {
                    "name": "Remove Drawio Noise",
                    "id": 34
                },
                "source_port": "\u2717",
                "target": {
                    "name": "",
                    "id": 0
                },
                "target_port": "\u2717"
            },
            {
                "dir": 2,
                "source": {
                    "name": "Combine Generated Code",
                    "id": 41
                },
                "source_port": "",
                "target": {
                    "name": "",
                    "id": 0
                },
                "target_port": ""
            },
            {
                "dir": 2,
                "source": {
                    "name": "Combine Generated Code",
                    "id": 41
                },
                "source_port": "\u2717",
                "target": {
                    "name": "",
                    "id": 0
                },
                "target_port": "\u2717"
            },
            {
                "dir": 2,
                "source": {
                    "name": "Cleanup",
                    "id": 21
                },
                "source_port": "\u2717",
                "target": {
                    "name": "",
                    "id": 0
                },
                "target_port": "\u2717"
            },
            {
                "dir": 2,
                "source": {
                    "name": "Exhale Procs",
                    "id": 15
                },
                "source_port": "\u2717",
                "target": {
                    "name": "",
                    "id": 0
                },
                "target_port": "\u2717"
            },
            {
                "dir": 2,
                "source": {
                    "name": "Prepare Macros",
                    "id": 9
                },
                "source_port": "\u2717",
                "target": {
                    "name": "",
                    "id": 0
                },
                "target_port": "\u2717"
            },
            {
                "dir": 2,
                "source": {
                    "name": "Read Text File",
                    "id": 33
                },
                "source_port": "\u2717",
                "target": {
                    "name": "",
                    "id": 0
                },
                "target_port": "\u2717"
            },
            {
                "dir": 2,
                "source": {
                    "name": "Generate Includer",
                    "id": 27
                },
                "source_port": "\u2717",
                "target": {
                    "name": "",
                    "id": 0
                },
                "target_port": "\u2717"
            },
            {
                "dir": 2,
                "source": {
                    "name": "Cleanup For Includer",
                    "id": 19
                },
                "source_port": "\u2717",
                "target": {
                    "name": "",
                    "id": 0
                },
                "target_port": "\u2717"
            }
        ]
    },
    {
        "file": "gen0d.drawio",
        "name": "Cleanup",
        "children": [
            {
                "name": "br2nl",
                "id": 8
            },
            {
                "name": "Cleanout HTML",
                "id": 11
            }
        ],
        "connections": [
            {
                "dir": 0,
                "source": {
                    "name": "",
                    "id": 0
                },
                "source_port": "",
                "target": {
                    "name": "Cleanout HTML",
                    "id": 11
                },
                "target_port": ""
            },
            {
                "dir": 1,
                "source": {
                    "name": "Cleanout HTML",
                    "id": 11
                },
                "source_port": "",
                "target": {
                    "name": "br2nl",
                    "id": 8
                },
                "target_port": ""
            },
            {
                "dir": 2,
                "source": {
                    "name": "br2nl",
                    "id": 8
                },
                "source_port": "\u2717",
                "target": {
                    "name": "",
                    "id": 0
                },
                "target_port": "\u2717"
            },
            {
                "dir": 2,
                "source": {
                    "name": "br2nl",
                    "id": 8
                },
                "source_port": "",
                "target": {
                    "name": "",
                    "id": 0
                },
                "target_port": ""
            },
            {
                "dir": 2,
                "source": {
                    "name": "Cleanout HTML",
                    "id": 11
                },
                "source_port": "\u2717",
                "target": {
                    "name": "",
                    "id": 0
                },
                "target_port": "\u2717"
            }
        ]
    },
    {
        "file": "gen0d.drawio",
        "name": "Prepare Macros",
        "children": [
            {
                "name": "Transpile",
                "id": 4
            },
            {
                "name": "'null.js'",
                "id": 13
            },
            {
                "name": "'encoder0D.rwr'",
                "id": 16
            },
            {
                "name": "'encoder0D.ohm'",
                "id": 19
            },
            {
                "name": "'encoder0D'",
                "id": 22
            }
        ],
        "connections": [
            {
                "dir": 0,
                "source": {
                    "name": "",
                    "id": 0
                },
                "source_port": "",
                "target": {
                    "name": "'null.js'",
                    "id": 13
                },
                "target_port": "\u237a"
            },
            {
                "dir": 0,
                "source": {
                    "name": "",
                    "id": 0
                },
                "source_port": "",
                "target": {
                    "name": "'encoder0D.rwr'",
                    "id": 16
                },
                "target_port": "\u237a"
            },
            {
                "dir": 0,
                "source": {
                    "name": "",
                    "id": 0
                },
                "source_port": "",
                "target": {
                    "name": "'encoder0D.ohm'",
                    "id": 19
                },
                "target_port": "\u237a"
            },
            {
                "dir": 0,
                "source": {
                    "name": "",
                    "id": 0
                },
                "source_port": "",
                "target": {
                    "name": "'encoder0D'",
                    "id": 22
                },
                "target_port": "\u237a"
            },
            {
                "dir": 0,
                "source": {
                    "name": "",
                    "id": 0
                },
                "source_port": "",
                "target": {
                    "name": "Transpile",
                    "id": 4
                },
                "target_port": "input"
            },
            {
                "dir": 1,
                "source": {
                    "name": "'null.js'",
                    "id": 13
                },
                "source_port": "\u237a",
                "target": {
                    "name": "Transpile",
                    "id": 4
                },
                "target_port": "rwrsupportfn"
            },
            {
                "dir": 1,
                "source": {
                    "name": "'encoder0D.rwr'",
                    "id": 16
                },
                "source_port": "\u237a",
                "target": {
                    "name": "Transpile",
                    "id": 4
                },
                "target_port": "rwrfn"
            },
            {
                "dir": 1,
                "source": {
                    "name": "'encoder0D.ohm'",
                    "id": 19
                },
                "source_port": "\u237a",
                "target": {
                    "name": "Transpile",
                    "id": 4
                },
                "target_port": "ohmfn"
            },
            {
                "dir": 1,
                "source": {
                    "name": "'encoder0D'",
                    "id": 22
                },
                "source_port": "\u237a",
                "target": {
                    "name": "Transpile",
                    "id": 4
                },
                "target_port": "grammar name"
            },
            {
                "dir": 2,
                "source": {
                    "name": "Transpile",
                    "id": 4
                },
                "source_port": "",
                "target": {
                    "name": "",
                    "id": 0
                },
                "target_port": ""
            },
            {
                "dir": 2,
                "source": {
                    "name": "Transpile",
                    "id": 4
                },
                "source_port": "\u2717",
                "target": {
                    "name": "",
                    "id": 0
                },
                "target_port": "\u2717"
            }
        ]
    },
    {
        "file": "gen0d.drawio",
        "name": "Remove Drawio Noise",
        "children": [
            {
                "name": "Transpile",
                "id": 4
            },
            {
                "name": "'null.js'",
                "id": 13
            },
            {
                "name": "'stripHTML.rwr'",
                "id": 16
            },
            {
                "name": "'stripHTML.ohm'",
                "id": 19
            },
            {
                "name": "'stripHTML'",
                "id": 22
            }
        ],
        "connections": [
            {
                "dir": 0,
                "source": {
                    "name": "",
                    "id": 0
                },
                "source_port": "",
                "target": {
                    "name": "'null.js'",
                    "id": 13
                },
                "target_port": "\u237a"
            },
            {
                "dir": 0,
                "source": {
                    "name": "",
                    "id": 0
                },
                "source_port": "",
                "target": {
                    "name": "'stripHTML.rwr'",
                    "id": 16
                },
                "target_port": "\u237a"
            },
            {
                "dir": 0,
                "source": {
                    "name": "",
                    "id": 0
                },
                "source_port": "",
                "target": {
                    "name": "'stripHTML.ohm'",
                    "id": 19
                },
                "target_port": "\u237a"
            },
            {
                "dir": 0,
                "source": {
                    "name": "",
                    "id": 0
                },
                "source_port": "",
                "target": {
                    "name": "'stripHTML'",
                    "id": 22
                },
                "target_port": "\u237a"
            },
            {
                "dir": 0,
                "source": {
                    "name": "",
                    "id": 0
                },
                "source_port": "",
                "target": {
                    "name": "Transpile",
                    "id": 4
                },
                "target_port": "input"
            },
            {
                "dir": 1,
                "source": {
                    "name": "'null.js'",
                    "id": 13
                },
                "source_port": "\u237a",
                "target": {
                    "name": "Transpile",
                    "id": 4
                },
                "target_port": "rwrsupportfn"
            },
            {
                "dir": 1,
                "source": {
                    "name": "'stripHTML.rwr'",
                    "id": 16
                },
                "source_port": "\u237a",
                "target": {
                    "name": "Transpile",
                    "id": 4
                },
                "target_port": "rwrfn"
            },
            {
                "dir": 1,
                "source": {
                    "name": "'stripHTML.ohm'",
                    "id": 19
                },
                "source_port": "\u237a",
                "target": {
                    "name": "Transpile",
                    "id": 4
                },
                "target_port": "ohmfn"
            },
            {
                "dir": 1,
                "source": {
                    "name": "'stripHTML'",
                    "id": 22
                },
                "source_port": "\u237a",
                "target": {
                    "name": "Transpile",
                    "id": 4
                },
                "target_port": "grammar name"
            },
            {
                "dir": 2,
                "source": {
                    "name": "Transpile",
                    "id": 4
                },
                "source_port": "",
                "target": {
                    "name": "",
                    "id": 0
                },
                "target_port": ""
            },
            {
                "dir": 2,
                "source": {
                    "name": "Transpile",
                    "id": 4
                },
                "source_port": "\u2717",
                "target": {
                    "name": "",
                    "id": 0
                },
                "target_port": "\u2717"
            }
        ]
    },
    {
        "file": "gen0d.drawio",
        "name": "Cleanout HTML",
        "children": [
            {
                "name": "Transpile",
                "id": 4
            },
            {
                "name": "'null.js'",
                "id": 13
            },
            {
                "name": "'rmHTML.rwr'",
                "id": 16
            },
            {
                "name": "'rmHTML.ohm'",
                "id": 19
            },
            {
                "name": "'rmHTML'",
                "id": 22
            }
        ],
        "connections": [
            {
                "dir": 0,
                "source": {
                    "name": "",
                    "id": 0
                },
                "source_port": "",
                "target": {
                    "name": "'null.js'",
                    "id": 13
                },
                "target_port": "\u237a"
            },
            {
                "dir": 0,
                "source": {
                    "name": "",
                    "id": 0
                },
                "source_port": "",
                "target": {
                    "name": "'rmHTML.rwr'",
                    "id": 16
                },
                "target_port": "\u237a"
            },
            {
                "dir": 0,
                "source": {
                    "name": "",
                    "id": 0
                },
                "source_port": "",
                "target": {
                    "name": "'rmHTML.ohm'",
                    "id": 19
                },
                "target_port": "\u237a"
            },
            {
                "dir": 0,
                "source": {
                    "name": "",
                    "id": 0
                },
                "source_port": "",
                "target": {
                    "name": "'rmHTML'",
                    "id": 22
                },
                "target_port": "\u237a"
            },
            {
                "dir": 0,
                "source": {
                    "name": "",
                    "id": 0
                },
                "source_port": "",
                "target": {
                    "name": "Transpile",
                    "id": 4
                },
                "target_port": "input"
            },
            {
                "dir": 1,
                "source": {
                    "name": "'null.js'",
                    "id": 13
                },
                "source_port": "\u237a",
                "target": {
                    "name": "Transpile",
                    "id": 4
                },
                "target_port": "rwrsupportfn"
            },
            {
                "dir": 1,
                "source": {
                    "name": "'rmHTML.rwr'",
                    "id": 16
                },
                "source_port": "\u237a",
                "target": {
                    "name": "Transpile",
                    "id": 4
                },
                "target_port": "rwrfn"
            },
            {
                "dir": 1,
                "source": {
                    "name": "'rmHTML.ohm'",
                    "id": 19
                },
                "source_port": "\u237a",
                "target": {
                    "name": "Transpile",
                    "id": 4
                },
                "target_port": "ohmfn"
            },
            {
                "dir": 1,
                "source": {
                    "name": "'rmHTML'",
                    "id": 22
                },
                "source_port": "\u237a",
                "target": {
                    "name": "Transpile",
                    "id": 4
                },
                "target_port": "grammar name"
            },
            {
                "dir": 2,
                "source": {
                    "name": "Transpile",
                    "id": 4
                },
                "source_port": "",
                "target": {
                    "name": "",
                    "id": 0
                },
                "target_port": ""
            },
            {
                "dir": 2,
                "source": {
                    "name": "Transpile",
                    "id": 4
                },
                "source_port": "\u2717",
                "target": {
                    "name": "",
                    "id": 0
                },
                "target_port": "\u2717"
            }
        ]
    },
    {
        "file": "gen0d.drawio",
        "name": "Combine Generated Code",
        "children": [
            {
                "name": "String Concatenate",
                "id": 7
            },
            {
                "name": "'<br>package generated<br>import \"core:fmt\"<br>import \"0d/odin/0d\"<br><br>'",
                "id": 14
            },
            {
                "name": "String Concatenate",
                "id": 18
            }
        ],
        "connections": [
            {
                "dir": 0,
                "source": {
                    "name": "",
                    "id": 0
                },
                "source_port": "gen",
                "target": {
                    "name": "'<br>package generated<br>import \"core:fmt\"<br>import \"0d/odin/0d\"<br><br>'",
                    "id": 14
                },
                "target_port": "\u237a"
            },
            {
                "dir": 0,
                "source": {
                    "name": "",
                    "id": 0
                },
                "source_port": "gen",
                "target": {
                    "name": "String Concatenate",
                    "id": 18
                },
                "target_port": "1"
            },
            {
                "dir": 0,
                "source": {
                    "name": "",
                    "id": 0
                },
                "source_port": "inc",
                "target": {
                    "name": "String Concatenate",
                    "id": 18
                },
                "target_port": "2"
            },
            {
                "dir": 1,
                "source": {
                    "name": "'<br>package generated<br>import \"core:fmt\"<br>import \"0d/odin/0d\"<br><br>'",
                    "id": 14
                },
                "source_port": "\u237a",
                "target": {
                    "name": "String Concatenate",
                    "id": 7
                },
                "target_port": "1"
            },
            {
                "dir": 1,
                "source": {
                    "name": "String Concatenate",
                    "id": 18
                },
                "source_port": "",
                "target": {
                    "name": "String Concatenate",
                    "id": 7
                },
                "target_port": "2"
            },
            {
                "dir": 2,
                "source": {
                    "name": "String Concatenate",
                    "id": 7
                },
                "source_port": "\u2717",
                "target": {
                    "name": "",
                    "id": 0
                },
                "target_port": "\u2717"
            },
            {
                "dir": 2,
                "source": {
                    "name": "String Concatenate",
                    "id": 7
                },
                "source_port": "",
                "target": {
                    "name": "",
                    "id": 0
                },
                "target_port": ""
            },
            {
                "dir": 2,
                "source": {
                    "name": "String Concatenate",
                    "id": 18
                },
                "source_port": "\u2717",
                "target": {
                    "name": "",
                    "id": 0
                },
                "target_port": "\u2717"
            }
        ]
    },
    {
        "file": "gen0d.drawio",
        "name": "Generate Includer",
        "children": [
            {
                "name": "Transpile",
                "id": 5
            },
            {
                "name": "'}'",
                "id": 14
            },
            {
                "name": "'incs.rwr'",
                "id": 15
            },
            {
                "name": "'incs.ohm'",
                "id": 18
            },
            {
                "name": "'incs'",
                "id": 21
            },
            {
                "name": "String Concatenate",
                "id": 29
            },
            {
                "name": "String Concatenate",
                "id": 30
            },
            {
                "name": "'<br>generated_components_to_include_in_project :: proc (leaves: ^[dynamic]zd.Leaf_Template) {'",
                "id": 32
            },
            {
                "name": "'procssupport.js'",
                "id": 34
            }
        ],
        "connections": [
            {
                "dir": 0,
                "source": {
                    "name": "",
                    "id": 0
                },
                "source_port": "",
                "target": {
                    "name": "'incs.ohm'",
                    "id": 18
                },
                "target_port": "\u237a"
            },
            {
                "dir": 0,
                "source": {
                    "name": "",
                    "id": 0
                },
                "source_port": "",
                "target": {
                    "name": "'}'",
                    "id": 14
                },
                "target_port": "\u237a"
            },
            {
                "dir": 0,
                "source": {
                    "name": "",
                    "id": 0
                },
                "source_port": "",
                "target": {
                    "name": "'incs'",
                    "id": 21
                },
                "target_port": "\u237a"
            },
            {
                "dir": 0,
                "source": {
                    "name": "",
                    "id": 0
                },
                "source_port": "",
                "target": {
                    "name": "'incs.rwr'",
                    "id": 15
                },
                "target_port": "\u237a"
            },
            {
                "dir": 0,
                "source": {
                    "name": "",
                    "id": 0
                },
                "source_port": "",
                "target": {
                    "name": "'procssupport.js'",
                    "id": 34
                },
                "target_port": "\u237a"
            },
            {
                "dir": 0,
                "source": {
                    "name": "",
                    "id": 0
                },
                "source_port": "",
                "target": {
                    "name": "'<br>generated_components_to_include_in_project :: proc (leaves: ^[dynamic]zd.Leaf_Template) {'",
                    "id": 32
                },
                "target_port": "\u237a"
            },
            {
                "dir": 0,
                "source": {
                    "name": "",
                    "id": 0
                },
                "source_port": "",
                "target": {
                    "name": "Transpile",
                    "id": 5
                },
                "target_port": "input"
            },
            {
                "dir": 1,
                "source": {
                    "name": "'<br>generated_components_to_include_in_project :: proc (leaves: ^[dynamic]zd.Leaf_Template) {'",
                    "id": 32
                },
                "source_port": "\u237a",
                "target": {
                    "name": "String Concatenate",
                    "id": 30
                },
                "target_port": "1"
            },
            {
                "dir": 1,
                "source": {
                    "name": "Transpile",
                    "id": 5
                },
                "source_port": "",
                "target": {
                    "name": "String Concatenate",
                    "id": 30
                },
                "target_port": "2"
            },
            {
                "dir": 1,
                "source": {
                    "name": "'incs'",
                    "id": 21
                },
                "source_port": "\u237a",
                "target": {
                    "name": "Transpile",
                    "id": 5
                },
                "target_port": "grammar name"
            },
            {
                "dir": 1,
                "source": {
                    "name": "'incs.ohm'",
                    "id": 18
                },
                "source_port": "\u237a",
                "target": {
                    "name": "Transpile",
                    "id": 5
                },
                "target_port": "ohmfn"
            },
            {
                "dir": 1,
                "source": {
                    "name": "'incs.rwr'",
                    "id": 15
                },
                "source_port": "\u237a",
                "target": {
                    "name": "Transpile",
                    "id": 5
                },
                "target_port": "rwrfn"
            },
            {
                "dir": 1,
                "source": {
                    "name": "'procssupport.js'",
                    "id": 34
                },
                "source_port": "\u237a",
                "target": {
                    "name": "Transpile",
                    "id": 5
                },
                "target_port": "rwrsupportfn"
            },
            {
                "dir": 1,
                "source": {
                    "name": "'}'",
                    "id": 14
                },
                "source_port": "\u237a",
                "target": {
                    "name": "String Concatenate",
                    "id": 29
                },
                "target_port": "2"
            },
            {
                "dir": 1,
                "source": {
                    "name": "String Concatenate",
                    "id": 30
                },
                "source_port": "",
                "target": {
                    "name": "String Concatenate",
                    "id": 29
                },
                "target_port": "1"
            },
            {
                "dir": 2,
                "source": {
                    "name": "String Concatenate",
                    "id": 30
                },
                "source_port": "\u2717",
                "target": {
                    "name": "",
                    "id": 0
                },
                "target_port": "\u2717"
            },
            {
                "dir": 2,
                "source": {
                    "name": "String Concatenate",
                    "id": 29
                },
                "source_port": "",
                "target": {
                    "name": "",
                    "id": 0
                },
                "target_port": ""
            },
            {
                "dir": 2,
                "source": {
                    "name": "String Concatenate",
                    "id": 29
                },
                "source_port": "\u2717",
                "target": {
                    "name": "",
                    "id": 0
                },
                "target_port": "\u2717"
            },
            {
                "dir": 2,
                "source": {
                    "name": "Transpile",
                    "id": 5
                },
                "source_port": "\u2717",
                "target": {
                    "name": "",
                    "id": 0
                },
                "target_port": "\u2717"
            }
        ]
    },
    {
        "file": "gen0d.drawio",
        "name": "Cleanup For Includer",
        "children": [
            {
                "name": "Cleanout HTML",
                "id": 5
            }
        ],
        "connections": [
            {
                "dir": 0,
                "source": {
                    "name": "",
                    "id": 0
                },
                "source_port": "",
                "target": {
                    "name": "Cleanout HTML",
                    "id": 5
                },
                "target_port": ""
            },
            {
                "dir": 2,
                "source": {
                    "name": "Cleanout HTML",
                    "id": 5
                },
                "source_port": "",
                "target": {
                    "name": "",
                    "id": 0
                },
                "target_port": ""
            },
            {
                "dir": 2,
                "source": {
                    "name": "Cleanout HTML",
                    "id": 5
                },
                "source_port": "\u2717",
                "target": {
                    "name": "",
                    "id": 0
                },
                "target_port": "\u2717"
            }
        ]
    }
]